[
  {
    "user": "U02ASPM0A6T",
    "text": "`/var/cache/pacman`ディレクトリを btrfs subvolume に外出ししてシンボリックリンクしてたら更新時に`/usr/bin/pacman`が消えてしまって焦りました\nそういうのやりたい場合はバインドマウントするといいようです\n<https://bbs.archlinux.org/viewtopic.php?id=241213>",
    "client_msg_id": "715bd8de-d89b-408a-bc9c-835e07695b10",
    "name": "yozigen",
    "img": "https://avatars.slack-edge.com/2021-08-15/2405164316960_50d7f6e8be23e5b2a0eb_24.jpg",
    "time": "2022/01/11 00:23:17",
    "link": "https://archlinuxjp.slack.com/archives/C0GFH3RHU/p1641825545074500"
  },
  {
    "user": "U019C7VLZ4G",
    "text": "ARMもSystemReadyが必須になってACPIとかが全てに載ればx64みたいにLinux入れるだけでだいたい動くみたいになるんだろうなぁと思ってる",
    "client_msg_id": "ad46f1ea-0656-4634-bf62-d28ab2375c16",
    "name": "getalotofmail",
    "img": "https://secure.gravatar.com/avatar/5a7f20688dc40b2989935a11bdfa25fe.jpg?s=24&d=https%3A%2F%2Fa.slack-edge.com%2Fdf10d%2Fimg%2Favatars%2Fava_0001-24.png",
    "time": "2022/01/11 00:23:17",
    "link": "https://archlinuxjp.slack.com/archives/C0GFH3RHU/p1641748545072400"
  },
  {
    "user": "UUWBU08TU",
    "text": "RPiの手軽さがよく分かりますね……、ARMもアーキテクチャ自体が作られたのは1990年とかなので、そこから組み込み向けで広く使われながら、20年くらい経ってやっとRPiが登場したことになります。\nArchLinuxARMの環境がきちんと整ったのもその前後なんじゃないかなと思っていて、そう考えると2010年からのプロジェクトであるRISC-Vはまだそのような段階に達していないような気もします。",
    "client_msg_id": "7f347fe6-8d1d-4a2e-be9e-125567018d75",
    "name": "nyaarch64",
    "img": "https://avatars.slack-edge.com/2020-06-22/1204027183412_7f7a529c9005aa8cce36_24.png",
    "time": "2022/01/10 02:24:13",
    "link": "https://archlinuxjp.slack.com/archives/C0GFH3RHU/p1641700223057700"
  },
  {
    "user": "U02ASPM0A6T",
    "text": "わずかながら＆どの程度使えるのかよくわかりませんが、Amazonで素朴に見たところハードウェアはいくつかありそうです\n<https://www.amazon.co.jp/s?k=risc-v>",
    "client_msg_id": "64973f93-0837-4bac-87df-51b757a02378",
    "name": "yozigen",
    "img": "https://avatars.slack-edge.com/2021-08-15/2405164316960_50d7f6e8be23e5b2a0eb_24.jpg",
    "time": "2022/01/09 13:23:03",
    "link": "https://archlinuxjp.slack.com/archives/C0GFH3RHU/p1641699700055000"
  },
  {
    "user": "UUWBU08TU",
    "text": "rv32iのバイナリだとほとんどのriscvマシンで動くんですかね？そもそもハードウェアを手軽に入手できるのか調べてないですが……",
    "client_msg_id": "b19fbf25-9450-4917-bd2c-403f8145d1dc",
    "name": "nyaarch64",
    "img": "https://avatars.slack-edge.com/2020-06-22/1204027183412_7f7a529c9005aa8cce36_24.png",
    "time": "2022/01/09 13:23:03",
    "link": "https://archlinuxjp.slack.com/archives/C0GFH3RHU/p1641699320054100"
  },
  {
    "user": "U02ASPM0A6T",
    "text": "これは今のところArchではなくGentooの領域ってことなんだろうなあ",
    "client_msg_id": "aeb8597a-0695-422f-a412-b1d0f6be15dd",
    "name": "yozigen",
    "img": "https://avatars.slack-edge.com/2021-08-15/2405164316960_50d7f6e8be23e5b2a0eb_24.jpg",
    "time": "2022/01/09 13:23:03",
    "link": "https://archlinuxjp.slack.com/archives/C0GFH3RHU/p1641698245053100"
  },
  {
    "user": "U02ASPM0A6T",
    "text": "ありがとうございます。とりあえず archlinuxarm みたいになってもらえればいいとは思うのですが、カーネルとGNUツールチェーンビルドしてエッジコンピューティングで使うあたりまでの仕組みはすぐできるとしても、ARM以上にCPUバリエーションが超乱立するので相当根本的な仕組みの革新がないとAURまで揃うのは無理で、個人利用のPCとしてはまだまだしばらくX86全盛時代が続きそうというところですね",
    "client_msg_id": "2059610a-0430-452f-b39b-4a5082af08ba",
    "name": "yozigen",
    "img": "https://avatars.slack-edge.com/2021-08-15/2405164316960_50d7f6e8be23e5b2a0eb_24.jpg",
    "time": "2022/01/09 12:18:45",
    "link": "https://archlinuxjp.slack.com/archives/C0GFH3RHU/p1641698157052600"
  },
  {
    "user": "UGA29R3FH",
    "text": "こうして考えるとAT互換機、BIOS、UEFI等の共通の仕組みは偉大だよなと",
    "client_msg_id": "663a5a1d-ce5f-4009-990a-8592ec328849",
    "name": "znmxodq1",
    "img": "https://avatars.slack-edge.com/2019-03-08/570571829091_2ca91fb0cc1ed2341fe0_24.png",
    "time": "2022/01/09 12:18:45",
    "link": "https://archlinuxjp.slack.com/archives/C0GFH3RHU/p1641695982051900"
  },
  {
    "user": "UPYQ3CUJ1",
    "text": "RISC-V は単に CPU  の仕様を定めるだけで、バイナリ自体の移植は原理的には単純にコンパイラが対応すれば簡単ですが、CPU 周り、基板の仕様はまちまちなので仕様をfix して系統的に皆が簡単に使えるような段階には至っていない状況なのではないでしょうか。だからこそ kernel では対応しようとも、パッケージのメンテナは  RISC-V をサポートするだけの労力を割けないでしょうし（する義務もないのでやるならアップストリームを待つか自分らでやる)。\n逆いそうならない限り、それは単に linux が動くだけであってパケージ提供が主な仕事である archlinux コミュニティが \"archlinux\" としてサポートする方向いは進んでいないのではないでしょうか。そもそも \"archlinux\" がサポートするアーキテクチャは x86_64 だけで、こうしている思想からもコミュニティとしても動かないかなと。（やるなら、archlinux コミュニティとしてではなく archlinuxarm みたいにしかなれないし、そうするには人が足りなさそう)",
    "client_msg_id": "aa45fee4-820d-4bc6-9f55-ba52b3d0e158",
    "name": "shota.af083",
    "img": "https://secure.gravatar.com/avatar/8806dbddb82d43065dd1190cfcf80c65.jpg?s=24&d=https%3A%2F%2Fa.slack-edge.com%2Fdf10d%2Fimg%2Favatars%2Fava_0023-24.png",
    "time": "2022/01/09 12:18:45",
    "link": "https://archlinuxjp.slack.com/archives/C0GFH3RHU/p1641694561051000"
  },
  {
    "user": "U02ASPM0A6T",
    "text": "RISC-VへのArch Linux移植ってどうなってるんでしょう\n非常に熱い領域に思えますが、英語版ArchWikiで調べても情報が全然出てこないのでかなり難しいんでしょうか\nこんなリポジトリや情報は見つけました\n• <https://github.com/archlinux-riscv>\n• <https://wiki.archlinux.org/title/User:Cmsigler/RISC-V>\n• <https://bbs.archlinux.org/search.php?action=search&amp;keywords=risc-v&amp;show_as=topics&amp;search=Submit>\n• <https://archlinuxarm.org/forum/search.php?keywords=risc-v>\n• <https://wiki.gentoo.org/wiki/Project:RISC-V>",
    "client_msg_id": "fd83525e-dd2e-418d-a60a-448525e52fa4",
    "name": "yozigen",
    "img": "https://avatars.slack-edge.com/2021-08-15/2405164316960_50d7f6e8be23e5b2a0eb_24.jpg",
    "time": "2022/01/09 11:38:14",
    "link": "https://archlinuxjp.slack.com/archives/C0GFH3RHU/p1641692785041300"
  },
  {
    "user": "U02ASPM0A6T",
    "text": "八幡さん、やはりHHKB開発の中心人物でした。知らなかった\n<https://note.com/tt_yawata/n/n5b750f8efc51|https://note.com/tt_yawata/n/n5b750f8efc51>",
    "client_msg_id": "fdd06314-b2ed-47b6-b159-ba320dbf705b",
    "name": "yozigen",
    "img": "https://avatars.slack-edge.com/2021-08-15/2405164316960_50d7f6e8be23e5b2a0eb_24.jpg",
    "time": "2022/01/09 11:38:14",
    "link": "https://archlinuxjp.slack.com/archives/C0GFH3RHU/p1641623582039500"
  },
  {
    "user": "U02ASPM0A6T",
    "text": "全然的はずれかもしれませんが、`wpa_supplicant`や`NetworkManager`なんかを止めて`iwd`と`networkd`だけでつなぐとか",
    "client_msg_id": "b8a104d1-347e-4f70-a488-a280eb24be85",
    "name": "yozigen",
    "img": "https://avatars.slack-edge.com/2021-08-15/2405164316960_50d7f6e8be23e5b2a0eb_24.jpg",
    "time": "2022/01/08 16:16:08",
    "link": "https://archlinuxjp.slack.com/archives/C0GFH3RHU/p1641618343038900"
  },
  {
    "user": "U0PM6EYR1",
    "text": "有線は優先されますからね",
    "client_msg_id": "42481820-43bc-42c6-b24f-b6800575baf9",
    "name": "raa0121",
    "img": "https://secure.gravatar.com/avatar/35b032d7b2d4182b0c2de1ef85ba91f2.jpg?s=24&d=https%3A%2F%2Fa.slack-edge.com%2Fdf10d%2Fimg%2Favatars%2Fava_0009-24.png",
    "time": "2022/01/08 14:17:00",
    "link": "https://archlinuxjp.slack.com/archives/C0GFH3RHU/p1641616568037200"
  },
  {
    "user": "U01J1GGMHDJ",
    "text": "そうなったら最強の解決法： 有線で繋ぐ:face_with_rolling_eyes:",
    "client_msg_id": "72fa354d-1454-4292-950d-606d3b38d507",
    "name": "naokihirokitomoki",
    "img": "https://avatars.slack-edge.com/2021-01-01/1607396797362_a9967cc229f49d114f8a_24.jpg",
    "time": "2022/01/08 14:17:01",
    "link": "https://archlinuxjp.slack.com/archives/C0GFH3RHU/p1641615922036700"
  },
  {
    "user": "U7NBCFT1S",
    "text": "返信ありがとうです。\n混雑しているの2．4Ghzも5Ghzも両方なんですよね。",
    "client_msg_id": "e33c6dd9-b0b4-4afd-882b-5d389634914c",
    "name": "no97yuu",
    "img": "https://avatars.slack-edge.com/2019-10-26/797548070962_e6a0da66a751d051ab30_24.jpg",
    "time": "2022/01/08 14:17:01",
    "link": "https://archlinuxjp.slack.com/archives/C0GFH3RHU/p1641612962035200"
  },
  {
    "user": "U02ASPM0A6T",
    "text": "HHKB作ったもう一人の人（おそらく和田教授と連携を進めて開発・製品化をハンドリングした中心人物？）のキーボード評論を見つけました。面白かったです\n<https://xtech.nikkei.com/atcl/nxt/column/18/01258/>\n昔の日本語キーボードで `~`、`^`、`＿`あたりのキー印字と入力内容に齟齬があったのがよくわからず不可解でしたが、メインフレームでの使用時のEBCDICに合わせていたという話があってびっくりです",
    "client_msg_id": "8a15d44e-eff6-4ac3-9168-e8b65a113792",
    "name": "yozigen",
    "img": "https://avatars.slack-edge.com/2021-08-15/2405164316960_50d7f6e8be23e5b2a0eb_24.jpg",
    "time": "2022/01/08 13:22:56",
    "link": "https://archlinuxjp.slack.com/archives/C0GFH3RHU/p1641612657033900"
  },
  {
    "user": "U02ASPM0A6T",
    "text": "• Wifiで2.4Ghz帯以外を使う\n• USB3.0機器（ハブなど）を延長ケーブル等使ってWifi送受信機から離す\n    ◦ USB3.1以上なら多分大丈夫？\n• Bluetooth機器をWifi送受信機から離す\n• Wifi送受信機の設置場所を変える\n参考URL\n• <https://oyamadenshi.com/wifi-usb-exp/>\n• <https://ctt.ne.jp/support/trouble/inter/lan.html>\n• <https://pctrouble.net/network/wlan_channel.html>",
    "client_msg_id": "ff53984b-1a54-4998-93e7-85afd862ea3a",
    "name": "yozigen",
    "img": "https://avatars.slack-edge.com/2021-08-15/2405164316960_50d7f6e8be23e5b2a0eb_24.jpg",
    "time": "2022/01/08 13:22:56",
    "link": "https://archlinuxjp.slack.com/archives/C0GFH3RHU/p1641576671025800"
  },
  {
    "user": "U01J1GGMHDJ",
    "text": "取り敢えず、チャンネル混雑は2.4GHz帯だろうから、5GHz帯をちゃんと使用してるかどうか調べた方が良さそう。",
    "client_msg_id": "babe2a9d-c552-49a3-acc7-79c310cdc307",
    "name": "naokihirokitomoki",
    "img": "https://avatars.slack-edge.com/2021-01-01/1607396797362_a9967cc229f49d114f8a_24.jpg",
    "time": "2022/01/08 03:20:46",
    "link": "https://archlinuxjp.slack.com/archives/C0GFH3RHU/p1641548309024200"
  },
  {
    "user": "U7NBCFT1S",
    "text": "wif接続でch混線時にめっちゃ通信速度が下がって（数百kpbs）厳しい。\nスマホは20M程度出しているので、Linux 側の設定でどうにかならないものだろうか。\n\n使用ドライバ：rtl88x2bu-dkms-git\n・国設定\n・パワーセーブOFF\nは設定済み。\n\n以下のwikiは見てます。\n<https://wiki.archlinux.jp/index.php/%E3%83%AF%E3%82%A4%E3%83%A4%E3%83%AC%E3%82%B9%E8%A8%AD%E5%AE%9A>",
    "client_msg_id": "fc3e0c54-9563-412a-87b4-686f09e06400",
    "name": "no97yuu",
    "img": "https://avatars.slack-edge.com/2019-10-26/797548070962_e6a0da66a751d051ab30_24.jpg",
    "time": "2022/01/07 19:19:39",
    "link": "https://archlinuxjp.slack.com/archives/C0GFH3RHU/p1641530518021800"
  },
  {
    "user": "U02ASPM0A6T",
    "text": "ありがとうございます。/etc/paru.conf に`SudoLoop`を入れておきました",
    "client_msg_id": "20e666e7-5c59-430b-9eae-8065721d974f",
    "name": "yozigen",
    "img": "https://avatars.slack-edge.com/2021-08-15/2405164316960_50d7f6e8be23e5b2a0eb_24.jpg",
    "time": "2022/01/07 14:17:33",
    "link": "https://archlinuxjp.slack.com/archives/C0GFH3RHU/p1641497482015300"
  },
  {
    "user": "U02BLTTQEL9",
    "text": "そんな感じぽいです。\n\n<https://github.com/Jguer/yay/search?q=sudoloop>\n<https://github.com/Morganamilo/paru/search?q=sudoloop>",
    "client_msg_id": "cbf67a71-b5c4-44a8-8b43-4360d523bfdc",
    "name": "buzz.taiki",
    "img": "https://avatars.slack-edge.com/2021-08-15/2388525195124_53543ae8a9c6189fc784_24.jpg",
    "time": "2022/01/07 05:17:00",
    "link": "https://archlinuxjp.slack.com/archives/C0GFH3RHU/p1641483981014600"
  },
  {
    "user": "U02SRH9D0DP",
    "text": "覚えておこう。\nタイムアウトしないで、パス入力状態で待機してくれる感じですかね。",
    "client_msg_id": "d80bae7a-0b31-4620-9f17-43046cae81bf",
    "name": "yasunori.kirin0418",
    "img": "https://avatars.slack-edge.com/2022-01-01/2921240792304_782ce2341a3138d14335_24.jpg",
    "time": "2022/01/07 01:27:47",
    "link": "https://archlinuxjp.slack.com/archives/C0GFH3RHU/p1641483906014300"
  },
  {
    "user": "U02SRH9D0DP",
    "text": "だいたい、トイレ行く前だったりコーヒー入れる前に実行して戻ってくると、タイムアウトしてましたってなる",
    "client_msg_id": "a7af8307-0f7a-4a69-8bf5-f70aa1685027",
    "name": "yasunori.kirin0418",
    "img": "https://avatars.slack-edge.com/2022-01-01/2921240792304_782ce2341a3138d14335_24.jpg",
    "time": "2022/01/07 01:27:47",
    "link": "https://archlinuxjp.slack.com/archives/C0GFH3RHU/p1641483843013900"
  },
  {
    "user": "U02BLTTQEL9",
    "text": "`--sudoloop` で勝利したかも。",
    "client_msg_id": "ab67f5ae-f6ca-4f27-9d92-01ebda16dcfc",
    "name": "buzz.taiki",
    "img": "https://avatars.slack-edge.com/2021-08-15/2388525195124_53543ae8a9c6189fc784_24.jpg",
    "time": "2022/01/07 01:27:47",
    "link": "https://archlinuxjp.slack.com/archives/C0GFH3RHU/p1641483818013500"
  },
  {
    "user": "U02SRH9D0DP",
    "text": "yay使ってますけど、放置してsudoタイムアウトしてると、心が無になる",
    "client_msg_id": "42823ca9-711b-4a78-9e98-d6f3fa7cb8e5",
    "name": "yasunori.kirin0418",
    "img": "https://avatars.slack-edge.com/2022-01-01/2921240792304_782ce2341a3138d14335_24.jpg",
    "time": "2022/01/07 01:27:48",
    "link": "https://archlinuxjp.slack.com/archives/C0GFH3RHU/p1641483767011900"
  },
  {
    "user": "U02BLTTQEL9",
    "text": "もしかして: `--sudoloop`",
    "client_msg_id": "06fa9b5f-3872-4eb1-aba8-46dadfe7d4f9",
    "name": "buzz.taiki",
    "img": "https://avatars.slack-edge.com/2021-08-15/2388525195124_53543ae8a9c6189fc784_24.jpg",
    "time": "2022/01/07 01:27:48",
    "link": "https://archlinuxjp.slack.com/archives/C0GFH3RHU/p1641483650009900"
  },
  {
    "user": "U02BLTTQEL9",
    "text": "`paru -Syu` とかやって放置してる間に sudo のパスワード読み込みがタイムアウトするのをもう100万回くらいやってる気がする。",
    "client_msg_id": "074c60d8-e749-441f-93f6-5329fc9aeeea",
    "name": "buzz.taiki",
    "img": "https://avatars.slack-edge.com/2021-08-15/2388525195124_53543ae8a9c6189fc784_24.jpg",
    "time": "2022/01/07 01:27:48",
    "link": "https://archlinuxjp.slack.com/archives/C0GFH3RHU/p1641483416008900"
  },
  {
    "user": "U019C7VLZ4G",
    "text": "規格の紹介記事と出荷開始のニュースはあるけど実物がまだ存在していない?",
    "client_msg_id": "1b175922-d199-418c-b29f-1973a4621f28",
    "name": "getalotofmail",
    "img": "https://secure.gravatar.com/avatar/5a7f20688dc40b2989935a11bdfa25fe.jpg?s=24&d=https%3A%2F%2Fa.slack-edge.com%2Fdf10d%2Fimg%2Favatars%2Fava_0001-24.png",
    "time": "2022/01/07 01:27:48",
    "link": "https://archlinuxjp.slack.com/archives/C0GFH3RHU/p1641481761008300"
  },
  {
    "user": "U019C7VLZ4G",
    "text": "<https://pc.watch.impress.co.jp/docs/news/1308395.html|https://pc.watch.impress.co.jp/docs/news/1308395.html>\nこれも売ってない",
    "client_msg_id": "b1329b93-e80a-4100-a0d2-95aa36bf6320",
    "name": "getalotofmail",
    "img": "https://secure.gravatar.com/avatar/5a7f20688dc40b2989935a11bdfa25fe.jpg?s=24&d=https%3A%2F%2Fa.slack-edge.com%2Fdf10d%2Fimg%2Favatars%2Fava_0001-24.png",
    "time": "2022/01/07 00:18:13",
    "link": "https://archlinuxjp.slack.com/archives/C0GFH3RHU/p1641481656006500"
  },
  {
    "user": "U0PM6EYR1",
    "text": "Express 初めて聞いた",
    "client_msg_id": "a7c514f9-be26-4826-8d99-3e29251c82f2",
    "name": "raa0121",
    "img": "https://secure.gravatar.com/avatar/35b032d7b2d4182b0c2de1ef85ba91f2.jpg?s=24&d=https%3A%2F%2Fa.slack-edge.com%2Fdf10d%2Fimg%2Favatars%2Fava_0009-24.png",
    "time": "2022/01/07 00:18:14",
    "link": "https://archlinuxjp.slack.com/archives/C0GFH3RHU/p1641481635006300"
  },
  {
    "user": "U019C7VLZ4G",
    "text": "micro SD Expressというmicro SDXCより高速かつ大容量の使用があるらしいのですがこれってまだカードとリーダーはまだ無い?\nAmazonで検索してもSDXCしか出てこない…\n<https://news.mynavi.jp/article/20190302-780546/|https://news.mynavi.jp/article/20190302-780546/>",
    "client_msg_id": "bdc88539-e4a3-430c-84fd-f3414f1e55b4",
    "name": "getalotofmail",
    "img": "https://secure.gravatar.com/avatar/5a7f20688dc40b2989935a11bdfa25fe.jpg?s=24&d=https%3A%2F%2Fa.slack-edge.com%2Fdf10d%2Fimg%2Favatars%2Fava_0001-24.png",
    "time": "2022/01/07 00:18:14",
    "link": "https://archlinuxjp.slack.com/archives/C0GFH3RHU/p1641481570005700"
  },
  {
    "user": "U019C7VLZ4G",
    "text": "あけおめ",
    "client_msg_id": "3673d690-6ea6-45d1-be16-271194b5cf50",
    "name": "getalotofmail",
    "img": "https://secure.gravatar.com/avatar/5a7f20688dc40b2989935a11bdfa25fe.jpg?s=24&d=https%3A%2F%2Fa.slack-edge.com%2Fdf10d%2Fimg%2Favatars%2Fava_0001-24.png",
    "time": "2022/01/07 00:18:14",
    "link": "https://archlinuxjp.slack.com/archives/C0GFH3RHU/p1641058965459200"
  },
  {
    "user": "U01HE1ENNJZ",
    "text": "あけましておめでとうございます\nみんな:archjp:",
    "client_msg_id": "a39b71bf-8536-4775-b889-a8d786cd9ee4",
    "name": "a3784197",
    "img": "https://avatars.slack-edge.com/2021-09-08/2452014575271_1a34f97ec1eeb20d8b71_24.png",
    "time": "2022/01/02 03:19:50",
    "link": "https://archlinuxjp.slack.com/archives/C0GFH3RHU/p1641000061456600"
  },
  {
    "user": "U0GFBAM8U",
    "text": ":archjp: ",
    "client_msg_id": "8ACFFBCC-6BDA-480E-BA28-141D1DE52A36",
    "name": "syui",
    "img": "https://avatars.slack-edge.com/2019-11-01/804484365746_6822720a4b6050bb8c57_24.png",
    "time": "2022/01/01 11:39:03",
    "link": "https://archlinuxjp.slack.com/archives/C0GFH3RHU/p1640995120455300"
  },
  {
    "user": "UBEFL3YLE",
    "text": "あけましてArch Linux",
    "client_msg_id": "1a6c46ed-5293-4d80-b265-bb3f57bb9d09",
    "name": "mail",
    "img": "https://secure.gravatar.com/avatar/23a2be2c0c837372158d36ca83743fe5.jpg?s=24&d=https%3A%2F%2Fa.slack-edge.com%2Fdf10d%2Fimg%2Favatars%2Fava_0018-24.png",
    "time": "2021/12/31,23:14:29",
    "link": "https://archlinuxjp.slack.com/archives/C0GFH3RHU/p1640992469454600"
  },
  {
    "user": "UGA29R3FH",
    "text": "多分今年も年中Arch Linuxを使い続けると思う",
    "client_msg_id": "9de17870-28cb-4380-a001-1c4cb2a63657",
    "name": "znmxodq1",
    "img": "https://avatars.slack-edge.com/2019-03-08/570571829091_2ca91fb0cc1ed2341fe0_24.png",
    "time": "2021/12/31,17:46:17",
    "link": "https://archlinuxjp.slack.com/archives/C0GFH3RHU/p1640972777453900"
  },
  {
    "user": "U01QTK2CP3K",
    "text": "あけましておめでとうございます\n今年もよろしくお願いします\n\nこれからもArchlinuxを布教していきます",
    "client_msg_id": "fb81d665-310b-4109-a287-0ff0ed2c2a8d",
    "name": "redohagi127",
    "img": "https://avatars.slack-edge.com/2021-12-31/2920219642768_bbde2736d2110b1a109d_24.jpg",
    "time": "2021/12/31,15:59:48",
    "link": "https://archlinuxjp.slack.com/archives/C0GFH3RHU/p1640966388452200"
  },
  {
    "user": "U01792411FA",
    "text": "今年もArch Linuxで遊ぼう",
    "client_msg_id": "c9de688b-03ff-4fa7-bed9-23fd99baf439",
    "name": "seekerkrt",
    "img": "https://avatars.slack-edge.com/2020-07-06/1229422291988_bb227d56e151807964f4_24.png",
    "time": "2021/12/31,15:58:45",
    "link": "https://archlinuxjp.slack.com/archives/C0GFH3RHU/p1640966325451300"
  },
  {
    "user": "U02ASPM0A6T",
    "text": "明けましておめでとうございます。昨年は大変お世話になりました。\n本年もよろしくお願いいたします:man-bowing:",
    "client_msg_id": "211470fc-a2ed-4e11-aaf4-3c559d460157",
    "name": "yozigen",
    "img": "https://avatars.slack-edge.com/2021-08-15/2405164316960_50d7f6e8be23e5b2a0eb_24.jpg",
    "time": "2021/12/31,15:35:12",
    "link": "https://archlinuxjp.slack.com/archives/C0GFH3RHU/p1640964912450600"
  },
  {
    "user": "U01QTK2CP3K",
    "text": "ipv6のポートを全開放していたONUがあったそうな、、、",
    "client_msg_id": "6ccb602a-df35-4d8c-9d28-8b26379aea72",
    "name": "redohagi127",
    "img": "https://avatars.slack-edge.com/2021-12-31/2920219642768_bbde2736d2110b1a109d_24.jpg",
    "time": "2021/12/31,12:00:47",
    "link": "https://archlinuxjp.slack.com/archives/C0GFH3RHU/p1640952047448300"
  },
  {
    "user": "UGA29R3FH",
    "text": "やばい",
    "client_msg_id": "7d98241e-ba40-4324-bbca-602811c677d0",
    "name": "znmxodq1",
    "img": "https://avatars.slack-edge.com/2019-03-08/570571829091_2ca91fb0cc1ed2341fe0_24.png",
    "time": "2021/12/31,11:56:17",
    "link": "https://archlinuxjp.slack.com/archives/C0GFH3RHU/p1640951777447700"
  },
  {
    "user": "U01QTK2CP3K",
    "text": "なお世の中にはfirewall設定の無効にしているONUを貸し出してるとんでも回線業者がいる、、、",
    "client_msg_id": "6c084184-cefd-4261-ba09-4d6af93b4c3b",
    "name": "redohagi127",
    "img": "https://avatars.slack-edge.com/2021-12-31/2920219642768_bbde2736d2110b1a109d_24.jpg",
    "time": "2021/12/31,11:53:07",
    "link": "https://archlinuxjp.slack.com/archives/C0GFH3RHU/p1640951587447400"
  },
  {
    "user": "UGA29R3FH",
    "text": "必要になった時はVPSに放り込んでるArchに向けてSSH Port Forwardingしかけてる",
    "client_msg_id": "9ce86eaa-fbe8-4795-8d17-44ddd8e8960d",
    "name": "znmxodq1",
    "img": "https://avatars.slack-edge.com/2019-03-08/570571829091_2ca91fb0cc1ed2341fe0_24.png",
    "time": "2021/12/31,11:31:12",
    "link": "https://archlinuxjp.slack.com/archives/C0GFH3RHU/p1640950272445800"
  },
  {
    "user": "UGA29R3FH",
    "text": "インフラマンではないので自宅のネットワークは一切公開してないな、今は",
    "client_msg_id": "3d541988-b393-4caf-89f0-1487070b19ef",
    "name": "znmxodq1",
    "img": "https://avatars.slack-edge.com/2019-03-08/570571829091_2ca91fb0cc1ed2341fe0_24.png",
    "time": "2021/12/31,11:30:38",
    "link": "https://archlinuxjp.slack.com/archives/C0GFH3RHU/p1640950238445200"
  },
  {
    "user": "UGA29R3FH",
    "text": "ルーターのNATが弾いてくれるの便利",
    "client_msg_id": "09c9d494-159b-4018-a495-9bf92be9ad8d",
    "name": "znmxodq1",
    "img": "https://avatars.slack-edge.com/2019-03-08/570571829091_2ca91fb0cc1ed2341fe0_24.png",
    "time": "2021/12/31,11:29:13",
    "link": "https://archlinuxjp.slack.com/archives/C0GFH3RHU/p1640950153444700"
  },
  {
    "user": "U01QTK2CP3K",
    "text": "ネットワーク系のセキュリティはルーターさんのファイアーウォールに任せてる",
    "client_msg_id": "5097924d-cff2-43f3-9178-10d421c52fbe",
    "name": "redohagi127",
    "img": "https://avatars.slack-edge.com/2021-12-31/2920219642768_bbde2736d2110b1a109d_24.jpg",
    "time": "2021/12/31,11:28:52",
    "link": "https://archlinuxjp.slack.com/archives/C0GFH3RHU/p1640950132444300"
  },
  {
    "user": "U01792411FA",
    "text": "ブラスターワームは猛威を奮った",
    "client_msg_id": "80abaa4d-7bbb-4c3a-9cfd-126fde67835c",
    "name": "seekerkrt",
    "img": "https://avatars.slack-edge.com/2020-07-06/1229422291988_bb227d56e151807964f4_24.png",
    "time": "2021/12/31,11:28:26",
    "link": "https://archlinuxjp.slack.com/archives/C0GFH3RHU/p1640950106443800"
  },
  {
    "user": "U01792411FA",
    "text": "昔は、無対策でネットに一瞬つないだだけでワームに感染とかありましたね",
    "client_msg_id": "668fd18a-0fe2-4b8e-9d63-a48503075f1a",
    "name": "seekerkrt",
    "img": "https://avatars.slack-edge.com/2020-07-06/1229422291988_bb227d56e151807964f4_24.png",
    "time": "2021/12/31,11:27:58",
    "link": "https://archlinuxjp.slack.com/archives/C0GFH3RHU/p1640950078443100"
  },
  {
    "user": "U01QTK2CP3K",
    "text": "作今のウイルス対策というかセキュリティ対策は、ソフト云々よりユーザーが気を付ける！のほうが対策になるような気がしてる。怪しいURLクリックするなとか、変なメール開くなとか、よくわからんUSBメモリ指すなとか、、、",
    "client_msg_id": "ad52d1d9-eefd-4dfd-a675-0e62895675c6",
    "name": "redohagi127",
    "img": "https://avatars.slack-edge.com/2021-12-31/2920219642768_bbde2736d2110b1a109d_24.jpg",
    "time": "2021/12/31,11:26:50",
    "link": "https://archlinuxjp.slack.com/archives/C0GFH3RHU/p1640950010442400"
  },
  {
    "user": "UGA29R3FH",
    "text": "うちの環境は余計な物がたくさん入ってるので使えない",
    "client_msg_id": "262de410-b513-454d-8621-00b3ccb51035",
    "name": "znmxodq1",
    "img": "https://avatars.slack-edge.com/2019-03-08/570571829091_2ca91fb0cc1ed2341fe0_24.png",
    "time": "2021/12/31,11:26:36",
    "link": "https://archlinuxjp.slack.com/archives/C0GFH3RHU/p1640949996442100"
  },
  {
    "user": "U01792411FA",
    "text": "copytoramかぁ",
    "client_msg_id": "8b5b4ebb-0873-4e4a-9476-f02dcf02c2da",
    "name": "seekerkrt",
    "img": "https://avatars.slack-edge.com/2020-07-06/1229422291988_bb227d56e151807964f4_24.png",
    "time": "2021/12/31,11:26:03",
    "link": "https://archlinuxjp.slack.com/archives/C0GFH3RHU/p1640949963441000"
  },
  {
    "user": "UGA29R3FH",
    "text": "メモリが潤沢にあって起動の遅さが許容できるなら便利だと思う",
    "client_msg_id": "41e65400-0163-4c0e-bd6b-92dd6b0aa7bd",
    "name": "znmxodq1",
    "img": "https://avatars.slack-edge.com/2019-03-08/570571829091_2ca91fb0cc1ed2341fe0_24.png",
    "time": "2021/12/31,11:24:07",
    "link": "https://archlinuxjp.slack.com/archives/C0GFH3RHU/p1640949847438600"
  },
  {
    "user": "U01QTK2CP3K",
    "text": "copytoram知らなかった、、、これ便利そう",
    "client_msg_id": "0bbb26a1-73b5-4404-8a09-228ce212a786",
    "name": "redohagi127",
    "img": "https://avatars.slack-edge.com/2021-12-31/2920219642768_bbde2736d2110b1a109d_24.jpg",
    "time": "2021/12/31,11:23:31",
    "link": "https://archlinuxjp.slack.com/archives/C0GFH3RHU/p1640949811437300"
  },
  {
    "user": "U01792411FA",
    "text": "昔ほどウィルスやワーム流行ってないし",
    "client_msg_id": "a47910fd-5cc2-498a-8233-f594b60189aa",
    "name": "seekerkrt",
    "img": "https://avatars.slack-edge.com/2020-07-06/1229422291988_bb227d56e151807964f4_24.png",
    "time": "2021/12/31,11:23:24",
    "link": "https://archlinuxjp.slack.com/archives/C0GFH3RHU/p1640949804437100"
  },
  {
    "user": "U01792411FA",
    "text": "昨今はWindows、Defenderだけで十分な気もしないでもない",
    "client_msg_id": "036a1062-f39a-4876-bf1c-5cc53e703cd4",
    "name": "seekerkrt",
    "img": "https://avatars.slack-edge.com/2020-07-06/1229422291988_bb227d56e151807964f4_24.png",
    "time": "2021/12/31,11:22:57",
    "link": "https://archlinuxjp.slack.com/archives/C0GFH3RHU/p1640949777436500"
  },
  {
    "user": "U01792411FA",
    "text": "デスクトップは保険としてNorton先生愛用してる",
    "client_msg_id": "55ff438f-52cf-4bae-bf1a-7b0166e36911",
    "name": "seekerkrt",
    "img": "https://avatars.slack-edge.com/2020-07-06/1229422291988_bb227d56e151807964f4_24.png",
    "time": "2021/12/31,11:21:48",
    "link": "https://archlinuxjp.slack.com/archives/C0GFH3RHU/p1640949708435900"
  },
  {
    "user": "UGA29R3FH",
    "text": "ライブシステムなら大抵copytoramオプションあるし(我らがarchisoにもある)使いたいんですよね",
    "client_msg_id": "157e88b4-7280-4a7e-b300-65cd137020fe",
    "name": "znmxodq1",
    "img": "https://avatars.slack-edge.com/2019-03-08/570571829091_2ca91fb0cc1ed2341fe0_24.png",
    "time": "2021/12/31,11:21:34",
    "link": "https://archlinuxjp.slack.com/archives/C0GFH3RHU/p1640949694435600"
  },
  {
    "user": "U01QTK2CP3K",
    "text": "RAM上にシステム展開とかするならなおさらほしい",
    "client_msg_id": "67b6d3f3-6e3a-47ff-bc7c-b4c4d02a2c7e",
    "name": "redohagi127",
    "img": "https://avatars.slack-edge.com/2021-12-31/2920219642768_bbde2736d2110b1a109d_24.jpg",
    "time": "2021/12/31,11:20:39",
    "link": "https://archlinuxjp.slack.com/archives/C0GFH3RHU/p1640949639434700"
  },
  {
    "user": "U01QTK2CP3K",
    "text": "まぁメモリはいくらあっても困らないんで、たくさんあればあるほどいいもんです",
    "client_msg_id": "70982971-7559-4364-b9d2-38082724a946",
    "name": "redohagi127",
    "img": "https://avatars.slack-edge.com/2021-12-31/2920219642768_bbde2736d2110b1a109d_24.jpg",
    "time": "2021/12/31,11:20:11",
    "link": "https://archlinuxjp.slack.com/archives/C0GFH3RHU/p1640949611434000"
  },
  {
    "user": "UGA29R3FH",
    "text": "タブレットでも下手するともっと欲しくなる",
    "client_msg_id": "98c9b8a5-ef6d-4578-a93e-4dd22b2ac836",
    "name": "znmxodq1",
    "img": "https://avatars.slack-edge.com/2019-03-08/570571829091_2ca91fb0cc1ed2341fe0_24.png",
    "time": "2021/12/31,11:19:05",
    "link": "https://archlinuxjp.slack.com/archives/C0GFH3RHU/p1640949545433400"
  },
  {
    "user": "U01QTK2CP3K",
    "text": "まぁ業務にもよるんでしょうが、4Gが許されるのは現代ではタブレット端末ぐらいだと思ってます。",
    "client_msg_id": "620752de-df08-4953-ae88-e94ba95ea3b1",
    "name": "redohagi127",
    "img": "https://avatars.slack-edge.com/2021-12-31/2920219642768_bbde2736d2110b1a109d_24.jpg",
    "time": "2021/12/31,11:17:11",
    "link": "https://archlinuxjp.slack.com/archives/C0GFH3RHU/p1640949431431800"
  },
  {
    "user": "UGA29R3FH",
    "text": "せめて16GBは欲しいところ",
    "client_msg_id": "9bd20252-0f95-49f3-91a0-65160921b69c",
    "name": "znmxodq1",
    "img": "https://avatars.slack-edge.com/2019-03-08/570571829091_2ca91fb0cc1ed2341fe0_24.png",
    "time": "2021/12/31,11:15:56",
    "link": "https://archlinuxjp.slack.com/archives/C0GFH3RHU/p1640949356430700"
  },
  {
    "user": "U01QTK2CP3K",
    "text": "laptopなら8Gでも許せるけど、デスクトップで8Gは正直認めたくない、、、",
    "client_msg_id": "5e70e59d-2752-4cce-a2a7-588161e7fc4d",
    "name": "redohagi127",
    "img": "https://avatars.slack-edge.com/2021-12-31/2920219642768_bbde2736d2110b1a109d_24.jpg",
    "time": "2021/12/31,11:14:50",
    "link": "https://archlinuxjp.slack.com/archives/C0GFH3RHU/p1640949290430200"
  },
  {
    "user": "UGA29R3FH",
    "text": "ブラウザ立ち上げてIDE(正確にはVimとLS)立ち上げてビルドするだけで死ぬことがある",
    "client_msg_id": "d91e7a48-7bd6-4543-96af-9f496996da30",
    "name": "znmxodq1",
    "img": "https://avatars.slack-edge.com/2019-03-08/570571829091_2ca91fb0cc1ed2341fe0_24.png",
    "time": "2021/12/31,11:13:18",
    "link": "https://archlinuxjp.slack.com/archives/C0GFH3RHU/p1640949198428900"
  },
  {
    "user": "UGA29R3FH",
    "text": "私なんてメモリ8GBのマシンでも人権の無さ感じることがあるのに…",
    "client_msg_id": "d1b322b4-5745-45e0-9a44-bc1a01134b92",
    "name": "znmxodq1",
    "img": "https://avatars.slack-edge.com/2019-03-08/570571829091_2ca91fb0cc1ed2341fe0_24.png",
    "time": "2021/12/31,11:12:35",
    "link": "https://archlinuxjp.slack.com/archives/C0GFH3RHU/p1640949155428200"
  },
  {
    "user": "UGA29R3FH",
    "text": "人権が無い",
    "client_msg_id": "7611fef2-0f94-46ed-ada1-0d2057d9691e",
    "name": "znmxodq1",
    "img": "https://avatars.slack-edge.com/2019-03-08/570571829091_2ca91fb0cc1ed2341fe0_24.png",
    "time": "2021/12/31,11:12:01",
    "link": "https://archlinuxjp.slack.com/archives/C0GFH3RHU/p1640949121427700"
  },
  {
    "user": "U01QTK2CP3K",
    "text": "そのうえ監視ソフト入れてるから、起動しただけでavailableRAMが1Gちょっと、、、なにしろと？ってなる\n\nマウスパッドのないlaptop出ないかな",
    "client_msg_id": "7253e4fc-04d6-4f6c-b2cc-73b5874c3275",
    "name": "redohagi127",
    "img": "https://avatars.slack-edge.com/2021-12-31/2920219642768_bbde2736d2110b1a109d_24.jpg",
    "time": "2021/12/31,11:11:45",
    "link": "https://archlinuxjp.slack.com/archives/C0GFH3RHU/p1640949105427500"
  },
  {
    "user": "U0GFBAM8U",
    "text": "今度、「タイル型ノーパスワードセキュリティ、オプションにキーバインド書き換えで更に強化パック」をおすすめしておきましょう",
    "client_msg_id": "936181cd-bae9-4dce-85dc-d2677b30136d",
    "name": "syui",
    "img": "https://avatars.slack-edge.com/2019-11-01/804484365746_6822720a4b6050bb8c57_24.png",
    "time": "2021/12/31,11:10:25",
    "link": "https://archlinuxjp.slack.com/archives/C0GFH3RHU/p1640949025426500"
  },
  {
    "user": "UGA29R3FH",
    "text": "あるある",
    "client_msg_id": "9075ae21-6017-4b06-9064-288ecac54dbb",
    "name": "znmxodq1",
    "img": "https://avatars.slack-edge.com/2019-03-08/570571829091_2ca91fb0cc1ed2341fe0_24.png",
    "time": "2021/12/31,11:09:20",
    "link": "https://archlinuxjp.slack.com/archives/C0GFH3RHU/p1640948960424700"
  },
  {
    "user": "U0GFBAM8U",
    "text": "つら",
    "client_msg_id": "a4fbecdc-0792-4a0b-a5ea-e0f3cacd6853",
    "name": "syui",
    "img": "https://avatars.slack-edge.com/2019-11-01/804484365746_6822720a4b6050bb8c57_24.png",
    "time": "2021/12/31,11:09:18",
    "link": "https://archlinuxjp.slack.com/archives/C0GFH3RHU/p1640948958424600"
  },
  {
    "user": "U01QTK2CP3K",
    "text": "でも情弱な会社の上層部が安心感のために社内の端末に入れるように指示しているせいで、バイト先の業務PCがあり得ないぐらい動かない、、、第三世代Celeronのメモリ４Gに何させてんねん！ってめっちゃ思ってる。",
    "client_msg_id": "9e2e1f27-a0ce-441e-a42f-a6ae448b2cd2",
    "name": "redohagi127",
    "img": "https://avatars.slack-edge.com/2021-12-31/2920219642768_bbde2736d2110b1a109d_24.jpg",
    "time": "2021/12/31,11:08:57",
    "link": "https://archlinuxjp.slack.com/archives/C0GFH3RHU/p1640948937424300"
  },
  {
    "user": "U01QTK2CP3K",
    "text": "ただでさえ重いOSをさらに重くしてどうする？って思っている",
    "client_msg_id": "2e7dc8b6-714b-4471-b662-75205918e5d0",
    "name": "redohagi127",
    "img": "https://avatars.slack-edge.com/2021-12-31/2920219642768_bbde2736d2110b1a109d_24.jpg",
    "time": "2021/12/31,11:06:13",
    "link": "https://archlinuxjp.slack.com/archives/C0GFH3RHU/p1640948773421800"
  },
  {
    "user": "U0GFBAM8U",
    "text": "...true(プログラム)",
    "client_msg_id": "41624884-b00b-4df1-b952-becc2fb9f3e1",
    "name": "syui",
    "img": "https://avatars.slack-edge.com/2019-11-01/804484365746_6822720a4b6050bb8c57_24.png",
    "time": "2021/12/31,11:06:00",
    "link": "https://archlinuxjp.slack.com/archives/C0GFH3RHU/p1640948760421400"
  },
  {
    "user": "UGA29R3FH",
    "text": "ウイルスバスター、存在がウイルスみたいなもの(暴言)",
    "client_msg_id": "80a9b0c9-30f4-43e9-b39a-9541017289bb",
    "name": "znmxodq1",
    "img": "https://avatars.slack-edge.com/2019-03-08/570571829091_2ca91fb0cc1ed2341fe0_24.png",
    "time": "2021/12/31,11:05:37",
    "link": "https://archlinuxjp.slack.com/archives/C0GFH3RHU/p1640948737420300"
  },
  {
    "user": "U0GFBAM8U",
    "text": "でもスマホはセキュリティパック定期購入してる人多いし、winはウィルスバスター入れてる人多い印象あったりで",
    "client_msg_id": "2e40103b-a49b-4e3f-a058-5a3514a09d51",
    "name": "syui",
    "img": "https://avatars.slack-edge.com/2019-11-01/804484365746_6822720a4b6050bb8c57_24.png",
    "time": "2021/12/31,11:05:16",
    "link": "https://archlinuxjp.slack.com/archives/C0GFH3RHU/p1640948716419600"
  },
  {
    "user": "U01QTK2CP3K",
    "text": "arch入れてるserverにもclamAV入れて動かしてますね。",
    "client_msg_id": "9348736a-5bc4-4974-b13c-57095751fba5",
    "name": "redohagi127",
    "img": "https://avatars.slack-edge.com/2021-12-31/2920219642768_bbde2736d2110b1a109d_24.jpg",
    "time": "2021/12/31,11:04:28",
    "link": "https://archlinuxjp.slack.com/archives/C0GFH3RHU/p1640948668418100"
  },
  {
    "user": "U0GFBAM8U",
    "text": "私もmicrosoftのdefenderで十分という意見",
    "client_msg_id": "5fbb35e7-843b-4764-a794-198de1e99a01",
    "name": "syui",
    "img": "https://avatars.slack-edge.com/2019-11-01/804484365746_6822720a4b6050bb8c57_24.png",
    "time": "2021/12/31,11:04:22",
    "link": "https://archlinuxjp.slack.com/archives/C0GFH3RHU/p1640948662417900"
  },
  {
    "user": "U01QTK2CP3K",
    "text": "スマホは何も入れてないですね\nlaptopにはclamAV入れて時々動かしてます\nwinはdefenderで十分派ですね、僕も",
    "client_msg_id": "1c883c9e-0607-41ba-8b92-05264a12fe00",
    "name": "redohagi127",
    "img": "https://avatars.slack-edge.com/2021-12-31/2920219642768_bbde2736d2110b1a109d_24.jpg",
    "time": "2021/12/31,11:03:39",
    "link": "https://archlinuxjp.slack.com/archives/C0GFH3RHU/p1640948619416700"
  },
  {
    "user": "UGA29R3FH",
    "text": "スマホはサンドボックスみたいなもんだしいらんでしょと思ってる(no root勢)しWindowsはDefenderで十分でしょ派",
    "client_msg_id": "0f779ee9-2433-41ba-b1e6-f078dc48fb72",
    "name": "znmxodq1",
    "img": "https://avatars.slack-edge.com/2019-03-08/570571829091_2ca91fb0cc1ed2341fe0_24.png",
    "time": "2021/12/31,11:02:38",
    "link": "https://archlinuxjp.slack.com/archives/C0GFH3RHU/p1640948558415600"
  },
  {
    "user": "U0GFBAM8U",
    "text": "スマホの場合はドコモセキュリティパックとかになるんですが",
    "client_msg_id": "c92262a3-cd61-4b14-8446-e4289264bfad",
    "name": "syui",
    "img": "https://avatars.slack-edge.com/2019-11-01/804484365746_6822720a4b6050bb8c57_24.png",
    "time": "2021/12/31,11:02:37",
    "link": "https://archlinuxjp.slack.com/archives/C0GFH3RHU/p1640948557415400"
  },
  {
    "user": "U0GFBAM8U",
    "text": "そういえば、みなさん、スマホとかwindowsとかでウィルスソフト入れてたりします?\nあれ逆に危ないと思うんですよねえ(あくまで個人的な意見",
    "client_msg_id": "19e3baf5-d90c-4946-b525-841e24102287",
    "name": "syui",
    "img": "https://avatars.slack-edge.com/2019-11-01/804484365746_6822720a4b6050bb8c57_24.png",
    "time": "2021/12/31,11:01:46",
    "link": "https://archlinuxjp.slack.com/archives/C0GFH3RHU/p1640948506413800"
  },
  {
    "user": "U01QTK2CP3K",
    "text": "macbookみたいなデザインでマウスパッドのないlaptopが発売されたら、タイル型WM入れて遊んでみたい",
    "client_msg_id": "2b7d744b-9b94-4dfd-b3bb-f14076e7610d",
    "name": "redohagi127",
    "img": "https://avatars.slack-edge.com/2021-12-31/2920219642768_bbde2736d2110b1a109d_24.jpg",
    "time": "2021/12/31,11:01:39",
    "link": "https://archlinuxjp.slack.com/archives/C0GFH3RHU/p1640948499413600"
  },
  {
    "user": "U0GFBAM8U",
    "text": "キーバインド上書きされてる場合はさらなるセキュリティ向上が可能です\n？「こ、これは...売れるぞっ！」",
    "client_msg_id": "577cc62a-9373-4fa1-93a7-41f3d36c338e",
    "name": "syui",
    "img": "https://avatars.slack-edge.com/2019-11-01/804484365746_6822720a4b6050bb8c57_24.png",
    "time": "2021/12/31,10:59:01",
    "link": "https://archlinuxjp.slack.com/archives/C0GFH3RHU/p1640948341411900"
  },
  {
    "user": "U01QTK2CP3K",
    "text": "ある意味情弱勢に対しては一定の効果のあるセキュリティであることは間違いない",
    "client_msg_id": "49964895-6bea-474f-b0e8-fab8373d2aa4",
    "name": "redohagi127",
    "img": "https://avatars.slack-edge.com/2021-12-31/2920219642768_bbde2736d2110b1a109d_24.jpg",
    "time": "2021/12/31,10:58:42",
    "link": "https://archlinuxjp.slack.com/archives/C0GFH3RHU/p1640948322411500"
  },
  {
    "user": "U01QTK2CP3K",
    "text": "「あいつのPC盗んでやったぜ！早速起動してみよ、、、やった！起動できた！あいつパスワードなしかよwww」\n「・・・どうやって操作するんだ？？？」",
    "client_msg_id": "05954054-0a6c-4590-b1d5-a88c9db6c8df",
    "name": "redohagi127",
    "img": "https://avatars.slack-edge.com/2021-12-31/2920219642768_bbde2736d2110b1a109d_24.jpg",
    "time": "2021/12/31,10:57:29",
    "link": "https://archlinuxjp.slack.com/archives/C0GFH3RHU/p1640948249410000"
  },
  {
    "user": "U8T8KB5M4",
    "text": "さらにデフォキーバインド全部上書きしてますね（セキュリティ意図はもちろんない）",
    "client_msg_id": "c4b5b230-1ef4-41cc-a1e7-5414b9a5715b",
    "name": "h.hata.ai.t",
    "img": "https://avatars.slack-edge.com/2019-08-19/732537331990_536f34e28226326cb4e8_24.png",
    "time": "2021/12/31,10:56:25",
    "link": "https://archlinuxjp.slack.com/archives/C0GFH3RHU/p1640948185408500"
  },
  {
    "user": "U0GFBAM8U",
    "text": "タイル型ノーパスワードセキュリティ",
    "client_msg_id": "160e2158-7749-4a2c-821d-1ac2bd3ff3e7",
    "name": "syui",
    "img": "https://avatars.slack-edge.com/2019-11-01/804484365746_6822720a4b6050bb8c57_24.png",
    "time": "2021/12/31,10:55:35",
    "link": "https://archlinuxjp.slack.com/archives/C0GFH3RHU/p1640948135406300"
  },
  {
    "user": "U01QTK2CP3K",
    "text": "タイル型ウインドウマネージャーは初見じゃ操作できん、、、",
    "client_msg_id": "4d2fa4e3-9560-465e-87d3-e8632452751c",
    "name": "redohagi127",
    "img": "https://avatars.slack-edge.com/2021-12-31/2920219642768_bbde2736d2110b1a109d_24.jpg",
    "time": "2021/12/31,10:55:02",
    "link": "https://archlinuxjp.slack.com/archives/C0GFH3RHU/p1640948102405900"
  },
  {
    "user": "UGA29R3FH",
    "text": "個別にtrustできたらいいんだけど",
    "client_msg_id": "94e2942a-c652-44fd-a991-bafd31054c53",
    "name": "znmxodq1",
    "img": "https://avatars.slack-edge.com/2019-03-08/570571829091_2ca91fb0cc1ed2341fe0_24.png",
    "time": "2021/12/31,10:54:41",
    "link": "https://archlinuxjp.slack.com/archives/C0GFH3RHU/p1640948081405500"
  },
  {
    "user": "UGA29R3FH",
    "text": "パスワードといえば、sudoersにNOPASSWD設定してるのもよくないなーと思いつつやめられてない",
    "client_msg_id": "039731a6-57f7-4f6f-b63e-a54dbb839e87",
    "name": "znmxodq1",
    "img": "https://avatars.slack-edge.com/2019-03-08/570571829091_2ca91fb0cc1ed2341fe0_24.png",
    "time": "2021/12/31,10:54:34",
    "link": "https://archlinuxjp.slack.com/archives/C0GFH3RHU/p1640948074405200"
  },
  {
    "user": "U0GFBAM8U",
    "text": "i3、初見だと、マジで操作わかんないと思う",
    "client_msg_id": "dadd1794-e7d6-4ff3-9a6f-c14636951f02",
    "name": "syui",
    "img": "https://avatars.slack-edge.com/2019-11-01/804484365746_6822720a4b6050bb8c57_24.png",
    "time": "2021/12/31,10:53:08",
    "link": "https://archlinuxjp.slack.com/archives/C0GFH3RHU/p1640947988404100"
  },
  {
    "user": "UGA29R3FH",
    "text": "外に持ち出すならちゃんとログインとLUKSの設定はします",
    "client_msg_id": "377e426f-d532-4c58-88ed-272b4e333bf9",
    "name": "znmxodq1",
    "img": "https://avatars.slack-edge.com/2019-03-08/570571829091_2ca91fb0cc1ed2341fe0_24.png",
    "time": "2021/12/31,10:53:04",
    "link": "https://archlinuxjp.slack.com/archives/C0GFH3RHU/p1640947984403900"
  },
  {
    "user": "U0GFBAM8U",
    "text": "まあ、そうですね笑",
    "client_msg_id": "b85fbac2-cd4d-4c2d-bc9d-7d33766fec6d",
    "name": "syui",
    "img": "https://avatars.slack-edge.com/2019-11-01/804484365746_6822720a4b6050bb8c57_24.png",
    "time": "2021/12/31,10:52:30",
    "link": "https://archlinuxjp.slack.com/archives/C0GFH3RHU/p1640947950402900"
  },
  {
    "user": "UGA29R3FH",
    "text": "うちの環境、i3なので知らん人が起動しても操作できないでしょ",
    "client_msg_id": "fe00403d-992c-4303-87ea-712be65a1566",
    "name": "znmxodq1",
    "img": "https://avatars.slack-edge.com/2019-03-08/570571829091_2ca91fb0cc1ed2341fe0_24.png",
    "time": "2021/12/31,10:52:07",
    "link": "https://archlinuxjp.slack.com/archives/C0GFH3RHU/p1640947927402400"
  },
  {
    "user": "UGA29R3FH",
    "text": "ただlaptopだとできないんよなぁ",
    "client_msg_id": "20881021-f60e-49d0-9965-b45f8b72358b",
    "name": "znmxodq1",
    "img": "https://avatars.slack-edge.com/2019-03-08/570571829091_2ca91fb0cc1ed2341fe0_24.png",
    "time": "2021/12/31,10:51:45",
    "link": "https://archlinuxjp.slack.com/archives/C0GFH3RHU/p1640947905402000"
  },
  {
    "user": "U01QTK2CP3K",
    "text": "いらなくなったUSBメモリのキャップに入れて、PCツールバックのポケットに入れてます",
    "client_msg_id": "f307c6fc-8507-4b17-a8c6-0267d82b5c8d",
    "name": "redohagi127",
    "img": "https://avatars.slack-edge.com/2021-12-31/2920219642768_bbde2736d2110b1a109d_24.jpg",
    "time": "2021/12/31,10:51:42",
    "link": "https://archlinuxjp.slack.com/archives/C0GFH3RHU/p1640947902401600"
  },
  {
    "user": "U0GFBAM8U",
    "text": "パスワード入力ログイン派のほうが多いのだろうか",
    "client_msg_id": "76515df7-4127-4733-8078-721c1b546938",
    "name": "syui",
    "img": "https://avatars.slack-edge.com/2019-11-01/804484365746_6822720a4b6050bb8c57_24.png",
    "time": "2021/12/31,10:51:39",
    "link": "https://archlinuxjp.slack.com/archives/C0GFH3RHU/p1640947899401500"
  },
  {
    "user": "UGA29R3FH",
    "text": "ライブディストロの体験がコンセプトなので自動ログインは外せない",
    "client_msg_id": "027f52e4-0d84-4a97-a1c7-d5e386427711",
    "name": "znmxodq1",
    "img": "https://avatars.slack-edge.com/2019-03-08/570571829091_2ca91fb0cc1ed2341fe0_24.png",
    "time": "2021/12/31,10:51:37",
    "link": "https://archlinuxjp.slack.com/archives/C0GFH3RHU/p1640947897401200"
  },
  {
    "user": "U0GFBAM8U",
    "text": "私はセキュリティ放置勢でパスワードなしの自動ログインしてるなあ",
    "client_msg_id": "9d28208c-ce17-41e1-acd5-7f11869dd0c3",
    "name": "syui",
    "img": "https://avatars.slack-edge.com/2019-11-01/804484365746_6822720a4b6050bb8c57_24.png",
    "time": "2021/12/31,10:50:45",
    "link": "https://archlinuxjp.slack.com/archives/C0GFH3RHU/p1640947845400000"
  },
  {
    "user": "UGA29R3FH",
    "text": "一般性が無い(Arch Wikiの情報が役に立たない部分がそれなりにある)\n運用に難がある(更新や設定の反映が面倒臭い)",
    "client_msg_id": "8215fd04-af67-4331-90ad-7fa48ccbe69b",
    "name": "znmxodq1",
    "img": "https://avatars.slack-edge.com/2019-03-08/570571829091_2ca91fb0cc1ed2341fe0_24.png",
    "time": "2021/12/31,10:49:55",
    "link": "https://archlinuxjp.slack.com/archives/C0GFH3RHU/p1640947795399300"
  },
  {
    "user": "U8T8KB5M4",
    "text": "Yubikeyどうやって持ち歩いてるか気になります。端子部分露出してるの気になってなんかいい感じに保護できないかなっていつも思ってるんですが。",
    "client_msg_id": "7170d62f-159a-436a-a4c9-83b7c1413f13",
    "name": "h.hata.ai.t",
    "img": "https://avatars.slack-edge.com/2019-08-19/732537331990_536f34e28226326cb4e8_24.png",
    "time": "2021/12/31,10:48:01",
    "link": "https://archlinuxjp.slack.com/archives/C0GFH3RHU/p1640947681397600"
  },
  {
    "user": "U0GFBAM8U",
    "text": "セキュリティ強そう",
    "client_msg_id": "adfc98af-4a80-474c-a57b-dcad16aa37c8",
    "name": "syui",
    "img": "https://avatars.slack-edge.com/2019-11-01/804484365746_6822720a4b6050bb8c57_24.png",
    "time": "2021/12/31,10:48:00",
    "link": "https://archlinuxjp.slack.com/archives/C0GFH3RHU/p1640947680397500"
  },
  {
    "user": "U0GFBAM8U",
    "text": "便利",
    "client_msg_id": "d85a8d43-9fde-48bf-b2e6-d2d1a5414215",
    "name": "syui",
    "img": "https://avatars.slack-edge.com/2019-11-01/804484365746_6822720a4b6050bb8c57_24.png",
    "time": "2021/12/31,10:47:53",
    "link": "https://archlinuxjp.slack.com/archives/C0GFH3RHU/p1640947673397300"
  },
  {
    "user": "UGA29R3FH",
    "text": "あまりに一般性が無いのと運用に難があるので手放しでおすすめはできないですが、電源切ると戻るシステムというのは乙な物ですよ",
    "client_msg_id": "8b2ba861-d1f3-4d48-a1a7-37d341556f8b",
    "name": "znmxodq1",
    "img": "https://avatars.slack-edge.com/2019-03-08/570571829091_2ca91fb0cc1ed2341fe0_24.png",
    "time": "2021/12/31,10:47:22",
    "link": "https://archlinuxjp.slack.com/archives/C0GFH3RHU/p1640947642396700"
  },
  {
    "user": "U01QTK2CP3K",
    "text": "laptopは取られたときに漏洩するの嫌だから暗号化に暗号化を重ねて、パスワードもショルダーハッキングされないようにYubikey使ってますね",
    "client_msg_id": "e4320191-4574-4aee-959e-929d827488df",
    "name": "redohagi127",
    "img": "https://avatars.slack-edge.com/2021-12-31/2920219642768_bbde2736d2110b1a109d_24.jpg",
    "time": "2021/12/31,10:46:36",
    "link": "https://archlinuxjp.slack.com/archives/C0GFH3RHU/p1640947596396000"
  },
  {
    "user": "U8T8KB5M4",
    "text": "皆さんのキッティングの話それぞれブログにしてもらいたい",
    "client_msg_id": "c7ccafad-461f-4a29-a24e-ce9cd5e60e31",
    "name": "h.hata.ai.t",
    "img": "https://avatars.slack-edge.com/2019-08-19/732537331990_536f34e28226326cb4e8_24.png",
    "time": "2021/12/31,10:46:10",
    "link": "https://archlinuxjp.slack.com/archives/C0GFH3RHU/p1640947570395200"
  },
  {
    "user": "U01792411FA",
    "text": "魔改造！",
    "client_msg_id": "8876824f-cb4a-434a-86b5-e9dcd895b310",
    "name": "seekerkrt",
    "img": "https://avatars.slack-edge.com/2020-07-06/1229422291988_bb227d56e151807964f4_24.png",
    "time": "2021/12/31,10:45:53",
    "link": "https://archlinuxjp.slack.com/archives/C0GFH3RHU/p1640947553394400"
  },
  {
    "user": "UGA29R3FH",
    "text": "実の所、魔改造archisoをベースにしていて生きているのでユーザーディレクトリ以外は全てライブシステムみたく揮発性なのですが、`/home`以下だけは実用上困るので起動時に日付でディレクトリを掘ってマウントしてます",
    "client_msg_id": "46f36746-9d60-4330-84d6-f431a64af1ae",
    "name": "znmxodq1",
    "img": "https://avatars.slack-edge.com/2019-03-08/570571829091_2ca91fb0cc1ed2341fe0_24.png",
    "time": "2021/12/31,10:45:32",
    "link": "https://archlinuxjp.slack.com/archives/C0GFH3RHU/p1640947532394100"
  },
  {
    "user": "U0GFBAM8U",
    "text": "ありがたい",
    "client_msg_id": "601e03c8-fb7d-40a1-95ba-b26355801053",
    "name": "syui",
    "img": "https://avatars.slack-edge.com/2019-11-01/804484365746_6822720a4b6050bb8c57_24.png",
    "time": "2021/12/31,10:43:59",
    "link": "https://archlinuxjp.slack.com/archives/C0GFH3RHU/p1640947439391400"
  },
  {
    "user": "U01792411FA",
    "text": "ラップトップでもデスクトップでも多分、/homeだけは分割しておくべき",
    "client_msg_id": "4666273e-cc44-48c3-9458-c2112f606221",
    "name": "seekerkrt",
    "img": "https://avatars.slack-edge.com/2020-07-06/1229422291988_bb227d56e151807964f4_24.png",
    "time": "2021/12/31,10:43:50",
    "link": "https://archlinuxjp.slack.com/archives/C0GFH3RHU/p1640947430391200"
  },
  {
    "user": "U8T8KB5M4",
    "text": "この辺の他の人の話聞けるのとても嬉しい",
    "client_msg_id": "d47b8d48-26cd-498d-8391-fbbacc48fa4e",
    "name": "h.hata.ai.t",
    "img": "https://avatars.slack-edge.com/2019-08-19/732537331990_536f34e28226326cb4e8_24.png",
    "time": "2021/12/31,10:43:15",
    "link": "https://archlinuxjp.slack.com/archives/C0GFH3RHU/p1640947395390500"
  },
  {
    "user": "UGA29R3FH",
    "text": "おうちマシンはdesktopなので特に暗号化してない",
    "client_msg_id": "91eb866a-d35c-467e-932d-476cf8589a7f",
    "name": "znmxodq1",
    "img": "https://avatars.slack-edge.com/2019-03-08/570571829091_2ca91fb0cc1ed2341fe0_24.png",
    "time": "2021/12/31,10:42:34",
    "link": "https://archlinuxjp.slack.com/archives/C0GFH3RHU/p1640947354389900"
  },
  {
    "user": "U01792411FA",
    "text": "ほんとはhomeぐらいは分割しとくべきなんだろうけど",
    "client_msg_id": "3e2b9a89-ba4e-4844-85cb-ea944ba46a07",
    "name": "seekerkrt",
    "img": "https://avatars.slack-edge.com/2020-07-06/1229422291988_bb227d56e151807964f4_24.png",
    "time": "2021/12/31,10:42:32",
    "link": "https://archlinuxjp.slack.com/archives/C0GFH3RHU/p1640947352389800"
  },
  {
    "user": "UGA29R3FH",
    "text": "laptopでやるならそのへんもちゃんと考えないといけないなー",
    "client_msg_id": "20ccf8e0-2920-458c-960c-18eb0daf0c0d",
    "name": "znmxodq1",
    "img": "https://avatars.slack-edge.com/2019-03-08/570571829091_2ca91fb0cc1ed2341fe0_24.png",
    "time": "2021/12/31,10:42:15",
    "link": "https://archlinuxjp.slack.com/archives/C0GFH3RHU/p1640947335389100"
  },
  {
    "user": "U01792411FA",
    "text": "EFI 500MiB 残りroot、メモリ多めに積んでるのでSwap取らない",
    "client_msg_id": "9de84b99-c1c2-42a1-87f6-d11aaf8daec2",
    "name": "seekerkrt",
    "img": "https://avatars.slack-edge.com/2020-07-06/1229422291988_bb227d56e151807964f4_24.png",
    "time": "2021/12/31,10:40:34",
    "link": "https://archlinuxjp.slack.com/archives/C0GFH3RHU/p1640947234388100"
  },
  {
    "user": "U01QTK2CP3K",
    "text": "laptopにNVMe-SSDとSATA-SSDぶち込んでるので、nvmeにブートローダーを、sataをLUKSで暗号化してホームディレクトリに使ってますね\nnvmeは`/boot` `/home` `/home` にいい感じに切ってますね\nsataのほうは復号化ファイルをnvmeに入れて、nvmeがマウントされていないと復号化できないようにしてます。",
    "client_msg_id": "4ab46139-3f21-4931-9111-27cfd9ab7276",
    "name": "redohagi127",
    "img": "https://avatars.slack-edge.com/2021-12-31/2920219642768_bbde2736d2110b1a109d_24.jpg",
    "time": "2021/12/31,10:40:33",
    "link": "https://archlinuxjp.slack.com/archives/C0GFH3RHU/p1640947233388000"
  },
  {
    "user": "UGA29R3FH",
    "text": "(なお `/data` 以下は散らかっている模様)",
    "client_msg_id": "cbf44a0e-c5fe-4ee0-a610-2a4daabf1ac7",
    "name": "znmxodq1",
    "img": "https://avatars.slack-edge.com/2019-03-08/570571829091_2ca91fb0cc1ed2341fe0_24.png",
    "time": "2021/12/31,10:39:43",
    "link": "https://archlinuxjp.slack.com/archives/C0GFH3RHU/p1640947183386300"
  },
  {
    "user": "UGA29R3FH",
    "text": "Linux的ではないディレクトリに突っ込んでおく利点としてディストロをスイッチしやすいというのがあります、後homeディレクトリも散らかりにくい",
    "client_msg_id": "014309de-c46e-445c-ac15-b3e966b61744",
    "name": "znmxodq1",
    "img": "https://avatars.slack-edge.com/2019-03-08/570571829091_2ca91fb0cc1ed2341fe0_24.png",
    "time": "2021/12/31,10:39:25",
    "link": "https://archlinuxjp.slack.com/archives/C0GFH3RHU/p1640947165385300"
  },
  {
    "user": "UGA29R3FH",
    "text": "標準的ではないので名前を何にするかが悩ましかった",
    "client_msg_id": "4fe69198-9cf4-444d-8505-970743daf8f2",
    "name": "znmxodq1",
    "img": "https://avatars.slack-edge.com/2019-03-08/570571829091_2ca91fb0cc1ed2341fe0_24.png",
    "time": "2021/12/31,10:37:59",
    "link": "https://archlinuxjp.slack.com/archives/C0GFH3RHU/p1640947079382700"
  },
  {
    "user": "UGA29R3FH",
    "text": "ホームディレクトリとか何とかの振り分けを全然やってない代わりにユーザーデータを全て `/data` 以下に置いてます",
    "client_msg_id": "4041b6a9-6fc2-471e-a74d-2a7ccaff774e",
    "name": "znmxodq1",
    "img": "https://avatars.slack-edge.com/2019-03-08/570571829091_2ca91fb0cc1ed2341fe0_24.png",
    "time": "2021/12/31,10:37:33",
    "link": "https://archlinuxjp.slack.com/archives/C0GFH3RHU/p1640947053381800"
  },
  {
    "user": "U8T8KB5M4",
    "text": "なんか久しぶりにインストールバトルやりたくなってきた…",
    "client_msg_id": "b724d600-ed14-4fd3-b3e4-09f6d9a1b73e",
    "name": "h.hata.ai.t",
    "img": "https://avatars.slack-edge.com/2019-08-19/732537331990_536f34e28226326cb4e8_24.png",
    "time": "2021/12/31,10:36:32",
    "link": "https://archlinuxjp.slack.com/archives/C0GFH3RHU/p1640946992380100"
  },
  {
    "user": "UGA29R3FH",
    "text": "メモリが少ないのでReal 8GB Swap 8GBくらいやってます",
    "client_msg_id": "f8aa764b-2451-4368-a9c3-bbe11b2ba59e",
    "name": "znmxodq1",
    "img": "https://avatars.slack-edge.com/2019-03-08/570571829091_2ca91fb0cc1ed2341fe0_24.png",
    "time": "2021/12/31,10:36:22",
    "link": "https://archlinuxjp.slack.com/archives/C0GFH3RHU/p1640946982379500"
  },
  {
    "user": "U0GFBAM8U",
    "text": "swapは作ってません",
    "client_msg_id": "235bc766-7057-468b-80ea-b2150df16bcf",
    "name": "syui",
    "img": "https://avatars.slack-edge.com/2019-11-01/804484365746_6822720a4b6050bb8c57_24.png",
    "time": "2021/12/31,10:35:55",
    "link": "https://archlinuxjp.slack.com/archives/C0GFH3RHU/p1640946955378300"
  },
  {
    "user": "UGA29R3FH",
    "text": "ここは自動化してないな(構築スクリプトで出てくるのさすが)",
    "client_msg_id": "86b367a3-77de-4356-9684-ac5ac49d6eaf",
    "name": "znmxodq1",
    "img": "https://avatars.slack-edge.com/2019-03-08/570571829091_2ca91fb0cc1ed2341fe0_24.png",
    "time": "2021/12/31,10:35:49",
    "link": "https://archlinuxjp.slack.com/archives/C0GFH3RHU/p1640946949378200"
  },
  {
    "user": "U0GFBAM8U",
    "text": "私は基本的にこんな感じでやってます\n```   parted /dev/${x} \\\n      -s mklabel gpt \\\n      -s mkpart primary ext2 0 200 \\\n      -s mkpart primary ext4 200 100% \\\n      -s p```",
    "client_msg_id": "2828ec28-08ae-4395-8dbc-9de5d30dfb88",
    "name": "syui",
    "img": "https://avatars.slack-edge.com/2019-11-01/804484365746_6822720a4b6050bb8c57_24.png",
    "time": "2021/12/31,10:35:21",
    "link": "https://archlinuxjp.slack.com/archives/C0GFH3RHU/p1640946921377600"
  },
  {
    "user": "U0GFBAM8U",
    "text": "みなさん、ディスクパーティション、どんな感じなのでしょう?",
    "client_msg_id": "3e4c9710-b13e-44fa-ba73-132da343b676",
    "name": "syui",
    "img": "https://avatars.slack-edge.com/2019-11-01/804484365746_6822720a4b6050bb8c57_24.png",
    "time": "2021/12/31,10:35:01",
    "link": "https://archlinuxjp.slack.com/archives/C0GFH3RHU/p1640946901377100"
  },
  {
    "user": "UGA29R3FH",
    "text": "セキュアブートは切るものだと覚えてる",
    "client_msg_id": "9f13c6c3-b2c0-4d85-ac22-0264e7b6baee",
    "name": "znmxodq1",
    "img": "https://avatars.slack-edge.com/2019-03-08/570571829091_2ca91fb0cc1ed2341fe0_24.png",
    "time": "2021/12/31,10:33:56",
    "link": "https://archlinuxjp.slack.com/archives/C0GFH3RHU/p1640946836376500"
  },
  {
    "user": "U01792411FA",
    "text": "Linuxのセキュアブートチャレンジしてみたいけど難しそう",
    "client_msg_id": "fa5d51a1-9598-4ca5-a611-01890d5406ca",
    "name": "seekerkrt",
    "img": "https://avatars.slack-edge.com/2020-07-06/1229422291988_bb227d56e151807964f4_24.png",
    "time": "2021/12/31,10:32:36",
    "link": "https://archlinuxjp.slack.com/archives/C0GFH3RHU/p1640946756375600"
  },
  {
    "user": "UGA29R3FH",
    "text": "GRUB楽だけど私にとっては完全なブラックボックス…",
    "client_msg_id": "a4437577-c4f7-4461-93e5-f5be7574cd47",
    "name": "znmxodq1",
    "img": "https://avatars.slack-edge.com/2019-03-08/570571829091_2ca91fb0cc1ed2341fe0_24.png",
    "time": "2021/12/31,10:32:30",
    "link": "https://archlinuxjp.slack.com/archives/C0GFH3RHU/p1640946750375500"
  },
  {
    "user": "U01QTK2CP3K",
    "text": "未だに署名セキュアブートしてないし、、、",
    "client_msg_id": "bd45a4cd-e33d-4bf8-a943-b26e414a9a08",
    "name": "redohagi127",
    "img": "https://avatars.slack-edge.com/2021-12-31/2920219642768_bbde2736d2110b1a109d_24.jpg",
    "time": "2021/12/31,10:32:08",
    "link": "https://archlinuxjp.slack.com/archives/C0GFH3RHU/p1640946728374900"
  },
  {
    "user": "U0GFBAM8U",
    "text": "grub楽なんだけど",
    "client_msg_id": "8BE2420C-9508-4881-8DF4-3B2C80BEAE46",
    "name": "syui",
    "img": "https://avatars.slack-edge.com/2019-11-01/804484365746_6822720a4b6050bb8c57_24.png",
    "time": "2021/12/31,10:31:56",
    "link": "https://archlinuxjp.slack.com/archives/C0GFH3RHU/p1640946716374600"
  },
  {
    "user": "U01792411FA",
    "text": "EFIのGRUB2ならほぼ設定いらないから楽です",
    "client_msg_id": "380c4e6e-df77-498d-88f8-13e0016ff7f6",
    "name": "seekerkrt",
    "img": "https://avatars.slack-edge.com/2020-07-06/1229422291988_bb227d56e151807964f4_24.png",
    "time": "2021/12/31,10:31:55",
    "link": "https://archlinuxjp.slack.com/archives/C0GFH3RHU/p1640946715374400"
  }
]
